server/__init__.py
server/server_.py
server/common/__init__.py
server/common/decos.py
server/common/descripts.py
server/common/errors.py
server/common/jim.py
server/common/metaclasses.py
server/common/utils.py
server/common/variables.py
server/logs/__init__.py
server/logs/client_log_config.py
server/logs/server_log_config.py
server/server/__init__.py
server/server/add_user.py
server/server/config_window.py
server/server/main.py
server/server/main_window.py
server/server/remove_user.py
server/server/server_db.py
server/server/stat_window.py
server/tests/__init__.py
server/tests/test_client.py
server/tests/test_jim.py
server/tests/test_server.py
server_pack_2try_version-0.8.7.dist-info/METADATA
server_pack_2try_version-0.8.7.dist-info/WHEEL
server_pack_2try_version-0.8.7.dist-info/top_level.txt
server_pack_2try_version-0.8.7.dist-info/RECORD
